tool_definitions/__init__.py
tool_definitions/config.py
tool_definitions/definitions.py
tools_definitions-1.0.3.dist-info/METADATA
tools_definitions-1.0.3.dist-info/WHEEL
tools_definitions-1.0.3.dist-info/top_level.txt
tools_definitions-1.0.3.dist-info/RECORD
