Metadata-Version: 2.1
Name: tools_definitions
Version: 1.0.3
Summary: Singlestore tools definitions
Home-page: https://github.com/singlestore-labs/singlestore-ai-tools
Author: Jai Khatri
Author-email: jkhatri@singlestore.com
Classifier: Programming Language :: Python :: 3
Classifier: License :: OSI Approved :: MIT License
Classifier: Operating System :: OS Independent
Requires-Python: >=3.6
Requires-Dist: requests
Requires-Dist: singlestoredb
Requires-Dist: python-dotenv
